MANIFEST.in
README.textile
setup.py
huDjango.egg-info/PKG-INFO
huDjango.egg-info/SOURCES.txt
huDjango.egg-info/dependency_links.txt
huDjango.egg-info/not-zip-safe
huDjango.egg-info/top_level.txt
hudjango/__init__.py
hudjango/decorators.py
hudjango/serializers.py
hudjango/validators.py
hudjango/auth/__init__.py
hudjango/auth/backends.py
hudjango/auth/decorators.py
hudjango/fields/__init__.py
hudjango/fields/couchdbfield.py
hudjango/fields/defaulting.py
hudjango/fields/scalingimagefield.py
hudjango/fields/testdefaulting.py
hudjango/fields/testscalingimagefield.py
hudjango/forms/__init__.py
hudjango/management/__init__.py
hudjango/management/commands/__init__.py
hudjango/management/commands/blame.py
hudjango/management/commands/couchdb-designs.py
hudjango/management/commands/couchdb-drop.py
hudjango/management/commands/couchdb-init.py
hudjango/management/commands/couchdb-validate-documents.py
hudjango/middleware/__init__.py
hudjango/middleware/clienttrack.py
hudjango/middleware/testthreadlocals.py
hudjango/middleware/threadlocals.py
hudjango/storage/CouchDBStorage.py
hudjango/storage/ImageServerStorage.py
hudjango/storage/__init__.py
hudjango/storage/dedupingS3storage.py
hudjango/templateloaders/__init__.py
hudjango/templateloaders/couchdbloader.py
hudjango/templatetags/__init__.py
hudjango/templatetags/hudjango.py
tests/__init__.py
tests/runtests.py
tests/settings_tests.py
tests/urls.py
tests/regressiontests/__init__.py
tests/regressiontests/auth_backends/__init__.py
tests/regressiontests/auth_backends/models.py
tests/regressiontests/auth_backends/tests.py
tests/regressiontests/auth_decorators/__init__.py
tests/regressiontests/auth_decorators/models.py
tests/regressiontests/auth_decorators/tests.py
tests/regressiontests/auth_decorators/views.py
tests/regressiontests/logger/__init__.py
tests/regressiontests/logger/models.py
tests/regressiontests/logger/tests.py
tests/regressiontests/serializers/__init__.py
tests/regressiontests/serializers/models.py
tests/regressiontests/serializers/tests.py