Metadata-Version: 1.0
Name: huDjango
Version: 0.95p1
Summary: various snippets for use with Django
Home-page: http://github.com/hudora/huDjango
Author: Maximillian Dornseif
Author-email: md@hudora.de
License: UNKNOWN
Platform: UNKNOWN
Classifier: License :: OSI Approved :: BSD License
Classifier: Intended Audience :: Developers
Classifier: Programming Language :: Python
